nxsconfigtool/AttributeDlg.py
nxsconfigtool/Component.py
nxsconfigtool/ComponentCreator.py
nxsconfigtool/ComponentDlg.py
nxsconfigtool/ComponentItem.py
nxsconfigtool/ComponentList.py
nxsconfigtool/ComponentModel.py
nxsconfigtool/ConfigurationServer.py
nxsconfigtool/ConnectDlg.py
nxsconfigtool/CreatorDlg.py
nxsconfigtool/DataSource.py
nxsconfigtool/DataSourceDlg.py
nxsconfigtool/DataSourceList.py
nxsconfigtool/DataSourceMethods.py
nxsconfigtool/DataSources.py
nxsconfigtool/DefinitionDlg.py
nxsconfigtool/DimensionsDlg.py
nxsconfigtool/DomTools.py
nxsconfigtool/EditCommands.py
nxsconfigtool/EditSlots.py
nxsconfigtool/ElementList.py
nxsconfigtool/Errors.py
nxsconfigtool/FieldDlg.py
nxsconfigtool/FileCommands.py
nxsconfigtool/FileSlots.py
nxsconfigtool/GroupDlg.py
nxsconfigtool/HelpForm.py
nxsconfigtool/HelpSlots.py
nxsconfigtool/ItemCommands.py
nxsconfigtool/ItemSlots.py
nxsconfigtool/LabeledObject.py
nxsconfigtool/LinkDlg.py
nxsconfigtool/ListCommands.py
nxsconfigtool/ListSlots.py
nxsconfigtool/Logger.py
nxsconfigtool/MainWindow.py
nxsconfigtool/MapDlg.py
nxsconfigtool/Merger.py
nxsconfigtool/NodeDlg.py
nxsconfigtool/Release.py
nxsconfigtool/RichAttributeDlg.py
nxsconfigtool/ServerCommands.py
nxsconfigtool/ServerSlots.py
nxsconfigtool/StrategyDlg.py
nxsconfigtool/WindowsSlots.py
nxsconfigtool/__init__.py
nxsconfigtool/qrc/resources.rcc
nxsconfigtool/ui/attributedlg.ui
nxsconfigtool/ui/clientdsdlg.ui
nxsconfigtool/ui/componentdlg.ui
nxsconfigtool/ui/connectdlg.ui
nxsconfigtool/ui/creatordlg.ui
nxsconfigtool/ui/datasourcedlg.ui
nxsconfigtool/ui/dbdsdlg.ui
nxsconfigtool/ui/definitiondlg.ui
nxsconfigtool/ui/dimensionsdlg.ui
nxsconfigtool/ui/elementlist.ui
nxsconfigtool/ui/fielddlg.ui
nxsconfigtool/ui/groupdlg.ui
nxsconfigtool/ui/linkdlg.ui
nxsconfigtool/ui/mainwindow.ui
nxsconfigtool/ui/pyevaldsdlg.ui
nxsconfigtool/ui/richattributedlg.ui
nxsconfigtool/ui/stdcreatordlg.ui
nxsconfigtool/ui/strategydlg.ui
nxsconfigtool/ui/tangodsdlg.ui
nxsconfigtool-2.1.2.dist-info/METADATA
nxsconfigtool-2.1.2.dist-info/WHEEL
nxsconfigtool-2.1.2.dist-info/top_level.txt
nxsconfigtool-2.1.2.dist-info/RECORD
