Metadata-Version: 2.1
Name: nxsconfigtool
Version: 2.1.2
Summary: Configuration tool  for creating components
Home-page: https://github.com/nexdatas/nxsdesigner/
Author: Jan Kotanski, Eugen Wintersberger , Halil Pasic
Author-email: jankotan@gmail.com, eugen.wintersberger@gmail.com, halil.pasic@gmail.com
Maintainer: Jan Kotanski, Eugen Wintersberger , Halil Pasic
Maintainer-email: jankotan@gmail.com, eugen.wintersberger@gmail.com, halil.pasic@gmail.com
License: GPLv3
Keywords: configuration writer Tango component nexus data
Platform: Linux
Platform: Windows
Platform: MacOS
Classifier: Development Status :: 5 - Production/Stable
Classifier: Intended Audience :: Science/Research
Classifier: Topic :: Scientific/Engineering :: Physics
Classifier: Topic :: Software Development :: Libraries :: Python Modules
Classifier: License :: OSI Approved :: GNU General Public License v2 (GPLv2)
Classifier: Programming Language :: Python :: 2.7
Classifier: Programming Language :: Python :: 3
Classifier: Programming Language :: Python :: 3.4
Classifier: Programming Language :: Python :: 3.5
Classifier: Programming Language :: Python :: 3.6
Classifier: Programming Language :: Python :: 3.7
Classifier: Programming Language :: Python :: 3.8
Classifier: Programming Language :: Python :: 3.9
Classifier: Programming Language :: Python :: 3.10
Classifier: Programming Language :: Python :: 3.11
Classifier: Programming Language :: Python :: 3.12
Classifier: Programming Language :: Python :: 3.13
Requires-Dist: nxstools
